releasecmd/__init__.py
releasecmd/__version__.py
releasecmd/_retry.py
releasecmd-0.10.4.dist-info/LICENSE
releasecmd-0.10.4.dist-info/METADATA
releasecmd-0.10.4.dist-info/WHEEL
releasecmd-0.10.4.dist-info/top_level.txt
releasecmd-0.10.4.dist-info/RECORD
