Metadata-Version: 2.1
Name: releasecmd
Version: 0.10.4
Summary: releasecmd is a release subcommand for setup.py (setuptools.setup). the subcommand creates a git tag and pushes and uploads packages to PyPI.
Home-page: https://github.com/thombashi/releasecmd
Author: Tsuyoshi Hombashi
Author-email: tsuyoshi.hombashi@gmail.com
License: MIT License
Project-URL: Changelog, https://github.com/thombashi/releasecmd/releases
Project-URL: Source, https://github.com/thombashi/releasecmd
Project-URL: Tracker, https://github.com/thombashi/releasecmd/issues
Keywords: release,setuptools
Classifier: Development Status :: 4 - Beta
Classifier: Framework :: Setuptools Plugin
Classifier: Intended Audience :: Developers
Classifier: Intended Audience :: Information Technology
Classifier: License :: OSI Approved :: MIT License
Classifier: Operating System :: OS Independent
Classifier: Programming Language :: Python :: 3
Classifier: Programming Language :: Python :: 3.8
Classifier: Programming Language :: Python :: 3.9
Classifier: Programming Language :: Python :: 3.10
Classifier: Programming Language :: Python :: 3.11
Classifier: Programming Language :: Python :: 3.12
Classifier: Programming Language :: Python :: 3 :: Only
Classifier: Topic :: Software Development :: Libraries
Classifier: Topic :: Software Development :: Libraries :: Python Modules
Classifier: Topic :: Software Development :: Version Control :: Git
Classifier: Topic :: Utilities
Requires-Python: >=3.8
License-File: LICENSE
Requires-Dist: packaging
Requires-Dist: setuptools
Requires-Dist: twine
